examples/__init__.py
examples/utils.py
examples/data_preprocessing/__init__.py
examples/data_preprocessing/imdb_dataset/__init__.py
examples/data_preprocessing/imdb_dataset/prepare_weak_imdb_data.py
examples/data_preprocessing/tac_based_dataset/__init__.py
examples/data_preprocessing/tac_based_dataset/utils/__init__.py
examples/data_preprocessing/tac_based_dataset/utils/lfs_reconstructor.py
examples/data_preprocessing/tac_based_dataset/utils/utils.py
examples/trainer/__init__.py
examples/trainer/preprocessing.py
examples/trainer/simple_auto_trainer/__init__.py
examples/trainer/simple_auto_trainer/auto_trainer_tutorial.py
examples/trainer/simple_auto_trainer/multi_trainer_tutorial.py
examples/trainer/wscrossweigh/__init__.py
examples/trainer/wscrossweigh/wscrossweigh_training_tutorial.py
examples/trainer/wscrossweigh/wscrossweigh_training_with_BiLSTM_tutorial.py
knodle/__init__.py
knodle/version.py
knodle/evaluation/__init__.py
knodle/evaluation/majority.py
knodle/evaluation/other_class_metrics.py
knodle/evaluation/plotting.py
knodle/evaluation/statistics.py
knodle/model/__init__.py
knodle/model/bidirectional_lstm_model.py
knodle/model/logisitc_regression_with_emb_layer.py
knodle/model/logistic_regression_model.py
knodle/model/EarlyStopping/__init__.py
knodle/trainer/__init__.py
knodle/trainer/auto_config.py
knodle/trainer/auto_trainer.py
knodle/trainer/config.py
knodle/trainer/multi_trainer.py
knodle/trainer/trainer.py
knodle/trainer/baseline/__init__.py
knodle/trainer/baseline/config.py
knodle/trainer/baseline/majority.py
knodle/trainer/cleanlab/__init__.py
knodle/trainer/cleanlab/cleanlab.py
knodle/trainer/cleanlab/config.py
knodle/trainer/cleanlab/latent_estimation.py
knodle/trainer/knn_aggregation/__init__.py
knodle/trainer/knn_aggregation/config.py
knodle/trainer/knn_aggregation/knn.py
knodle/trainer/knn_denoising/__init__.py
knodle/trainer/knn_denoising/config.py
knodle/trainer/knn_denoising/knn.py
knodle/trainer/snorkel/__init__.py
knodle-0.1.4.dist-info/LICENSE
knodle-0.1.4.dist-info/METADATA
knodle-0.1.4.dist-info/WHEEL
knodle-0.1.4.dist-info/top_level.txt
knodle-0.1.4.dist-info/RECORD
