Metadata-Version: 2.1
Name: knodle
Version: 0.1.4
Summary: Knowledge infused deep learning framework
Home-page: http://knodle.cc
Author: knodle
Author-email: knodle@cs.univie.ac.at
License: Apache 2.0
Project-URL: github, https://github.com/knodle/knodle
Project-URL: Bug Tracker, https://github.com/knodle/knodle/issues
Platform: UNKNOWN
Classifier: Development Status :: 2 - Pre-Alpha
Classifier: License :: OSI Approved :: Apache Software License
Classifier: Programming Language :: Python :: 3 :: Only
Classifier: Programming Language :: Python :: 3.6
Classifier: Programming Language :: Python :: 3.7
Classifier: Programming Language :: Python :: 3.8
Requires-Dist: joblib
Requires-Dist: tqdm
Requires-Dist: numpy (<1.20.0,>=1.16.5)
Requires-Dist: scipy
Requires-Dist: pandas
Requires-Dist: scikit-learn
Requires-Dist: torch
Requires-Dist: snorkel (<=0.9.7)
Requires-Dist: annoy
Requires-Dist: matplotlib
Requires-Dist: skorch
Requires-Dist: cleanlab
Provides-Extra: test
Requires-Dist: pytest ; extra == 'test'
Requires-Dist: pytest-cov ; extra == 'test'
